cluedin_magic/__init__.py
cluedin_magic/cluedin_magic.py
cluedin_magic-0.1.2.dist-info/LICENSE
cluedin_magic-0.1.2.dist-info/METADATA
cluedin_magic-0.1.2.dist-info/WHEEL
cluedin_magic-0.1.2.dist-info/RECORD
