Metadata-Version: 2.1
Name: cluedin-magic
Version: 0.1.2
Summary: IPython magic commands for CluedIn
Home-page: https://github.com/romaklimenko/cluedin-magic
License: MIT
Keywords: cluedin,mdm,master data management,ipython,magic,jupyter
Author: Roman Klimenko
Author-email: roman@klimenko.dk
Maintainer: Roman Klimenko
Maintainer-email: roman@klimenko.dk
Requires-Python: >=3.10,<4.0
Classifier: License :: OSI Approved :: MIT License
Classifier: Programming Language :: Python :: 3
Classifier: Programming Language :: Python :: 3.10
Classifier: Programming Language :: Python :: 3.11
Classifier: Programming Language :: Python :: 3.12
Requires-Dist: cluedin (>=2.5.0,<3.0.0)
Requires-Dist: ipython (>=7.34.0,<9.0.0)
Requires-Dist: pandas (>=2.1.4,<2.2.2)
Project-URL: Repository, https://github.com/romaklimenko/cluedin-magic
